{
  "project_info": {
    "project_number": "555250917520",
    "project_id": "rideshare-app-30b6c",
    "storage_bucket": "rideshare-app-30b6c.appspot.com"
  },
  "client": [
    {
      "client_info": {
        "mobilesdk_app_id": "1:555250917520:android:c485b0ae25d062d40a3815",
        "android_client_info": {
          "package_name": "edu.uga.cs.rideshareapp"
        }
      },
      "oauth_client": [],
      "api_key": [
        {
          "current_key": "AIzaSyB_2H2ApMROAlH-0dleyoQ7wDuUY_6dP-E"
        }
      ],
      "services": {
        "appinvite_service": {
          "other_platform_oauth_client": []
        }
      }
    }
  ],
  "configuration_version": "1"
}